spotmate/__init__.py
spotmate/actions.py
spotmate/main.py
spotmate/manager.py
spotmate/playlist_utils.py
spotmate/spotify_auth.py
spotmate/ui.py
spotmate-2.0.2.dist-info/METADATA
spotmate-2.0.2.dist-info/WHEEL
spotmate-2.0.2.dist-info/entry_points.txt
spotmate-2.0.2.dist-info/top_level.txt
spotmate-2.0.2.dist-info/RECORD
