Metadata-Version: 2.4
Name: spotmate
Version: 2.0.2
Summary: A command-line utility tool for Spotify playlists and albums
Author: Ankit Kumar Ravi
Project-URL: Homepage, https://github.com/riAssinstAr/Spot-Mate
Project-URL: Repository, https://github.com/riAssinstAr/Spot-Mate
Requires-Python: >=3.9
Requires-Dist: spotipy>=2.23.0
Requires-Dist: prompt-toolkit>=3.0
Requires-Dist: packaging>=23.0
